cr/sparse/__init__.py
cr/sparse/ef.py
cr/sparse/fom.py
cr/sparse/lop.py
cr/sparse/plots.py
cr/sparse/problems.py
cr/sparse/version.py
cr/sparse/_src/tracker.py
cr/sparse/_src/types.py
cr/sparse/_src/block/bsbl.py
cr/sparse/_src/block/util.py
cr/sparse/_src/cluster/kmeans.py
cr/sparse/_src/cluster/spectral.py
cr/sparse/_src/cluster/util.py
cr/sparse/_src/cluster/ssc/omp.py
cr/sparse/_src/cluster/ssc/util.py
cr/sparse/_src/cs/cs1bit/biht.py
cr/sparse/_src/cs/cs1bit/rfp.py
cr/sparse/_src/cs/cs1bit/util.py
cr/sparse/_src/cvx/focuss.py
cr/sparse/_src/cvx/l1ls.py
cr/sparse/_src/cvx/spgl1.py
cr/sparse/_src/cvx/adm/yall1.py
cr/sparse/_src/data/synthetic/random.py
cr/sparse/_src/data/synthetic/subspaces.py
cr/sparse/_src/dict/comparison.py
cr/sparse/_src/dict/grass.py
cr/sparse/_src/dict/props.py
cr/sparse/_src/dict/simple.py
cr/sparse/_src/dictlearn/standard.py
cr/sparse/_src/fom/bp_scd.py
cr/sparse/_src/fom/dantzig_scd.py
cr/sparse/_src/fom/defs.py
cr/sparse/_src/fom/focs_at.py
cr/sparse/_src/fom/fom.py
cr/sparse/_src/fom/l1rls.py
cr/sparse/_src/fom/lasso.py
cr/sparse/_src/fom/owl1rls.py
cr/sparse/_src/fom/scd.py
cr/sparse/_src/fom/util.py
cr/sparse/_src/geo/thresholding.py
cr/sparse/_src/geo/wavelets.py
cr/sparse/_src/lop/basic.py
cr/sparse/_src/lop/block_diag.py
cr/sparse/_src/lop/calculus.py
cr/sparse/_src/lop/conv.py
cr/sparse/_src/lop/dot.py
cr/sparse/_src/lop/dwt.py
cr/sparse/_src/lop/fft.py
cr/sparse/_src/lop/filters.py
cr/sparse/_src/lop/identity.py
cr/sparse/_src/lop/impl.py
cr/sparse/_src/lop/lop.py
cr/sparse/_src/lop/normest.py
cr/sparse/_src/lop/onb.py
cr/sparse/_src/lop/props.py
cr/sparse/_src/lop/random.py
cr/sparse/_src/lop/reshape.py
cr/sparse/_src/lop/special_matrices.py
cr/sparse/_src/lop/spread.py
cr/sparse/_src/lop/tv.py
cr/sparse/_src/lop/util.py
cr/sparse/_src/lop/windowed_op.py
cr/sparse/_src/opt/__init__.py
cr/sparse/_src/opt/cg.py
cr/sparse/_src/opt/pcg.py
cr/sparse/_src/opt/projections.py
cr/sparse/_src/opt/prox_to_smooth.py
cr_sparse-0.4.0.dist-info/LICENSE
cr_sparse-0.4.0.dist-info/METADATA
cr_sparse-0.4.0.dist-info/WHEEL
cr_sparse-0.4.0.dist-info/entry_points.txt
cr_sparse-0.4.0.dist-info/top_level.txt
cr_sparse-0.4.0.dist-info/RECORD
