Metadata-Version: 2.1
Name: cr-sparse
Version: 0.4.0
Summary: Accelerated sparse representations and compressive sensing
Home-page: https://carnotresearch.github.io/cr-sparse
Author: CR-Suite Development Team
Author-email: contact@carnotresearch.com
License: Apache 2.0: http://www.apache.org/licenses/LICENSE-2.0
Download-URL: https://github.com/carnotresearch/cr-sparse/archive/v0.4.0.tar.gz
Project-URL: Issue Tracker, https://github.com/carnotresearch/cr-sparse/issues
Keywords: Computer Vision
Platform: UNKNOWN
Classifier: Development Status :: 3 - Alpha
Classifier: Intended Audience :: Developers
Classifier: Topic :: Multimedia
Classifier: Topic :: Multimedia :: Video
Classifier: Topic :: Scientific/Engineering :: Image Processing
Classifier: Topic :: Scientific/Engineering :: Image Recognition
Classifier: License :: OSI Approved :: Apache Software License
Classifier: Operating System :: Unix
Classifier: Operating System :: POSIX
Classifier: Programming Language :: Python :: 3.8
Classifier: Programming Language :: Python :: 3.9
Classifier: Programming Language :: Python :: 3.10
Classifier: Programming Language :: Python :: Implementation :: CPython
Requires-Python: >=3.8
Requires-Dist: cr-nimble >=0.4.0
Requires-Dist: cr-wavelets >=0.4.0
Provides-Extra: dev
Provides-Extra: docs
Requires-Dist: sphinx >=3.3.0 ; extra == 'docs'
Requires-Dist: sphinx-rtd-theme >=0.5.0 ; extra == 'docs'
Requires-Dist: sphinxcontrib-katex >=0.7.1 ; extra == 'docs'
Requires-Dist: sphinxcontrib-bibtex >=1.0.0 ; extra == 'docs'
Requires-Dist: sphinx-autodoc-typehints >=1.11.1 ; extra == 'docs'
Requires-Dist: IPython >=7.16.1 ; extra == 'docs'
Requires-Dist: ipykernel >=5.3.4 ; extra == 'docs'
Requires-Dist: pandoc >=1.0.2 ; extra == 'docs'
Requires-Dist: nbsphinx >=0.8.0 ; extra == 'docs'
Requires-Dist: requests ; extra == 'docs'
Requires-Dist: cr-nimble >=0.4.0 ; extra == 'docs'
Provides-Extra: examples
Requires-Dist: cr-nimble >=0.4.0 ; extra == 'examples'
Requires-Dist: cr-wavelets >=0.4.0 ; extra == 'examples'
Provides-Extra: test
Requires-Dist: pytest ; extra == 'test'
Requires-Dist: pytest-cov ; extra == 'test'
